codelint/__init__.py
codelint/checker.py
codelint-0.6.dist-info/LICENSE
codelint-0.6.dist-info/METADATA
codelint-0.6.dist-info/WHEEL
codelint-0.6.dist-info/entry_points.txt
codelint-0.6.dist-info/top_level.txt
codelint-0.6.dist-info/RECORD
