Metadata-Version: 2.1
Name: codelint
Version: 0.6
Summary: A custom PEP 8 checker module
Home-page: https://github.com/Aditya-1998k/CodeLint
Author: Aditya Gupta
Author-email: aditya98gupta@gmail.com
Classifier: Programming Language :: Python :: 3
Classifier: License :: OSI Approved :: MIT License
Classifier: Operating System :: OS Independent
Requires-Python: >=3.6
License-File: LICENSE
